README.md
setup.py
django_distributed/__init__.py
django_distributed/session_engine.py
django_distributed.egg-info/PKG-INFO
django_distributed.egg-info/SOURCES.txt
django_distributed.egg-info/dependency_links.txt
django_distributed.egg-info/not-zip-safe
django_distributed.egg-info/requires.txt
django_distributed.egg-info/top_level.txt
django_distributed/router/__init__.py
django_distributed/router/cached_session_router.py
django_distributed/router/distributed_router.py